<?xml version="1.0" encoding="UTF-8"?>
<world>
	<decorations>
		<!-- List of decoration objects -->
	</decorations>
	<textureAreas>
		<area xywh="10,10,128,190">
			<texture><![CDATA[resources/images/backgrounds/grass02.png]]></texture>
		</area>
		<area xywh="10,220,128,190">
			<texture><![CDATA[resources/images/backgrounds/grass01.png]]></texture>
		</area>
	</textureAreas>
	<levels>
		<level xywh="10,20,10,10">
			<texture><![CDATA[resources/images/level/dev.png]]></texture>
			<map><![CDATA[resources/data/level/l01.xml]]></map>
		</level>
	</levels>
</world>